nbgoogleanalytics/__init__.py
nbgoogleanalytics/static/main.js
nbgoogleanalytics-0.1.0.dist-info/DESCRIPTION.rst
nbgoogleanalytics-0.1.0.dist-info/METADATA
nbgoogleanalytics-0.1.0.dist-info/RECORD
nbgoogleanalytics-0.1.0.dist-info/WHEEL
nbgoogleanalytics-0.1.0.dist-info/metadata.json
nbgoogleanalytics-0.1.0.dist-info/top_level.txt
