Metadata-Version: 2.0
Name: nbgoogleanalytics
Version: 0.1.0
Summary: Simple Jupyter extension to show how much resources (RAM) your notebook is using
Home-page: https://github.com/yuvipanda/nbgoogleanalytics
Author: Yuvi Panda
Author-email: UNKNOWN
License: UNKNOWN
Platform: UNKNOWN
Requires-Dist: notebook
